smartdistributor/__init__.py
smartdistributor/smartDistributor.py
smartdistributor-0.1.1.dev1.dist-info/DESCRIPTION.rst
smartdistributor-0.1.1.dev1.dist-info/METADATA
smartdistributor-0.1.1.dev1.dist-info/RECORD
smartdistributor-0.1.1.dev1.dist-info/WHEEL
smartdistributor-0.1.1.dev1.dist-info/metadata.json
smartdistributor-0.1.1.dev1.dist-info/top_level.txt
