Metadata-Version: 2.0
Name: smartdistributor
Version: 0.1.1.dev1
Summary: Multiprocessor task distributor
Home-page: UNKNOWN
Author: UNKNOWN
Author-email: UNKNOWN
License: UNKNOWN
